doing/__init__.py
doing-1.0.0.dist-info/DESCRIPTION.rst
doing-1.0.0.dist-info/METADATA
doing-1.0.0.dist-info/RECORD
doing-1.0.0.dist-info/WHEEL
doing-1.0.0.dist-info/entry_points.txt
doing-1.0.0.dist-info/metadata.json
doing-1.0.0.dist-info/top_level.txt
sample/__init__.py
sample/__main__.py
sample/version.py
sample/greet/__init__.py
sample/greet/english.py
sample/greet/spanish.py
