Metadata-Version: 2.0
Name: doing
Version: 1.0.0
Summary: doing implements hierarchical command lines
Home-page: http://bitbucket.org/apalala/doing
Author: Juancarlo Añez
Author-email: apalala@gmail.com
License: BSD License
Platform: UNKNOWN
Classifier: Development Status :: 5 - Production/Stable
Classifier: License :: OSI Approved :: BSD License
Classifier: Natural Language :: English
Classifier: Intended Audience :: Developers
Classifier: Intended Audience :: System Administrators
Classifier: Environment :: Console
Classifier: Operating System :: OS Independent
Classifier: Programming Language :: Python :: 3.5
Classifier: Programming Language :: Python :: 3.6
Classifier: Topic :: Software Development :: User Interfaces
Classifier: Topic :: System :: Installation/Setup
Classifier: Topic :: System :: Shells
Classifier: Topic :: Utilities
